README.md
setup.py
kerneltree.egg-info/PKG-INFO
kerneltree.egg-info/SOURCES.txt
kerneltree.egg-info/dependency_links.txt
kerneltree.egg-info/requires.txt
kerneltree.egg-info/top_level.txt
src/__init__.py
src/ckerneltree.pxd
src/compiler.h
src/interval_csv.c
src/interval_tree.c
src/interval_tree.h
src/interval_tree_generic.h
src/interval_tree_test.c
src/kerneltree.c
src/kerneltree.pyx
src/rbtree.c
src/rbtree.h
src/rbtree_augmented.h