Metadata-Version: 1.0
Name: kerneltree
Version: 0.0.5
Summary: Ultrafast interval tree implementation.
Home-page: http://github.com/endrebak/kerneltree
Author: Endre Bakken Stovner
Author-email: endrebak85@gmail.com
License: ['GPL2']
Keywords: intervaltree
Platform: UNKNOWN
